MANIFEST.in
README.md
README.rst
requirements.txt
setup.cfg
setup.py
mongocapsule/__init__.py
mongocapsule/capsule.py
mongocapsule/documents.py
mongocapsule/queryset.py
mongocapsule.egg-info/PKG-INFO
mongocapsule.egg-info/SOURCES.txt
mongocapsule.egg-info/dependency_links.txt
mongocapsule.egg-info/requires.txt
mongocapsule.egg-info/top_level.txt