Metadata-Version: 1.1
Name: mongocapsule
Version: 0.1.2
Summary: Encapsulated MongoEngine.
Home-page: https://github.com/prashnts/mongocapsule
Author: Prashant Sinha
Author-email: prashant@ducic.ac.in
License: MIT
Download-URL: https://github.com/prashnts/mongocapsule/tarball/0.1.2
Platform: UNKNOWN
Classifier: Development Status :: 3 - Alpha
Classifier: Environment :: Web Environment
Classifier: Intended Audience :: Developers
Classifier: License :: OSI Approved :: MIT License
Classifier: Operating System :: OS Independent
Classifier: Programming Language :: Python
Classifier: Programming Language :: Python :: 2
Classifier: Programming Language :: Python :: 2.6
Classifier: Programming Language :: Python :: 2.7
Classifier: Programming Language :: Python :: 3
Classifier: Programming Language :: Python :: 3.2
Classifier: Programming Language :: Python :: 3.3
Classifier: Programming Language :: Python :: 3.4
Classifier: Topic :: Internet :: WWW/HTTP :: Dynamic Content
Classifier: Topic :: Software Development :: Libraries :: Python Modules
